AUTHORS.rst
CONTRIBUTING.rst
HISTORY.rst
LICENSE
MANIFEST.in
README.rst
setup.cfg
setup.py
contactsheet/__init__.py
contactsheet/cli.py
contactsheet/contactsheet.py
contactsheet.egg-info/PKG-INFO
contactsheet.egg-info/SOURCES.txt
contactsheet.egg-info/dependency_links.txt
contactsheet.egg-info/entry_points.txt
contactsheet.egg-info/not-zip-safe
contactsheet.egg-info/requires.txt
contactsheet.egg-info/top_level.txt
docs/Makefile
docs/authors.rst
docs/conf.py
docs/contributing.rst
docs/history.rst
docs/index.rst
docs/installation.rst
docs/make.bat
docs/readme.rst
docs/usage.rst
tests/test_contactsheet.py