Metadata-Version: 1.1
Name: contactsheet
Version: 0.1.0
Summary: Contactsheet compiles a set of images into a single contact sheet image.
Home-page: https://github.com/paul-butcher/contactsheet
Author: Paul Butcher
Author-email: paul.butcher@gmail.com
License: MIT license
Keywords: contactsheet
Platform: UNKNOWN
Classifier: Development Status :: 2 - Pre-Alpha
Classifier: Intended Audience :: Developers
Classifier: License :: OSI Approved :: MIT License
Classifier: Natural Language :: English
Classifier: Programming Language :: Python :: 2
Classifier: Programming Language :: Python :: 2.7
Classifier: Programming Language :: Python :: 3
Classifier: Programming Language :: Python :: 3.4
Classifier: Programming Language :: Python :: 3.5
Classifier: Programming Language :: Python :: 3.6
